README.md
setup.cfg
setup.py
luas/__init__.py
luas/api.py
luas.py.egg-info/PKG-INFO
luas.py.egg-info/SOURCES.txt
luas.py.egg-info/dependency_links.txt
luas.py.egg-info/top_level.txt
luas/models/__init__.py