Metadata-Version: 2.1
Name: luas.py
Version: 0.2
Summary: Python module for interacting with Dublin Luas real-time API
Home-page: https://github.com/ronanmu/luas.py
Author: Ronan Murray
Author-email: ronanmu@users.noreply.github.com
License: MIT
Download-URL: https://github.com/ronanmu/luas.py/tarball/0.2
Keywords: luas,transport,dublin,ireland,tram
Platform: UNKNOWN
Classifier: Intended Audience :: Developers
Classifier: License :: OSI Approved :: MIT License
Requires: requests
